{
  "info": {
    "name": "Mini CRM Backend",
    "version": "1.1.0",
    "schema": "https://schema.getpostman.com/json/collection/v2.1.0/collection.json",
    "description": "Postman collection for the Mini CRM backend v1.1. Uses Laravel Sanctum authentication. Includes auth, client, follow-up, communication, and dashboard requests.\n\n**New in v1.1:**\n- Sanctum token authentication\n- Company field in clients\n- Enhanced dashboard metrics (top sales reps, avg communication frequency)\n- Improved client status logic"
  },
  "item": [
    {
      "name": "Auth",
      "item": [
        {
          "name": "Login",
          "request": {
            "method": "POST",
            "header": [
              {
                "key": "Content-Type",
                "value": "application/json"
              }
            ],
            "body": {
              "mode": "raw",
              "raw": "{\n  \"email\": \"admin@crm.test\",\n  \"password\": \"password\"\n}"
            },
            "url": {
              "raw": "{{base_url}}/api/v1/auth/login",
              "host": [
                "{{base_url}}"
              ],
              "path": [
                "api",
                "v1",
                "auth",
                "login"
              ]
            }
          },
          "response": []
        },
        {
          "name": "Me",
          "request": {
            "method": "GET",
            "header": [
              {
                "key": "Authorization",
                "value": "Bearer {{access_token}}"
              }
            ],
            "url": {
              "raw": "{{base_url}}/api/v1/auth/me",
              "host": [
                "{{base_url}}"
              ],
              "path": [
                "api",
                "v1",
                "auth",
                "me"
              ]
            }
          },
          "response": []
        },
        {
          "name": "Update Follow Up",
          "request": {
            "method": "PATCH",
            "header": [
              {
                "key": "Authorization",
                "value": "Bearer {{access_token}}"
              },
              {
                "key": "Content-Type",
                "value": "application/json"
              }
            ],
            "body": {
              "mode": "raw",
              "raw": "{\n  \"status\": \"completed\",\n  \"notes\": \"Client signed contract\"\n}"
            },
            "url": {
              "raw": "{{base_url}}/api/v1/follow-ups/{{follow_up_id}}",
              "host": [
                "{{base_url}}"
              ],
              "path": [
                "api",
                "v1",
                "follow-ups",
                "{{follow_up_id}}"
              ]
            }
          },
          "response": []
        },
        {
          "name": "Delete Follow Up",
          "request": {
            "method": "DELETE",
            "header": [
              {
                "key": "Authorization",
                "value": "Bearer {{access_token}}"
              }
            ],
            "url": {
              "raw": "{{base_url}}/api/v1/follow-ups/{{follow_up_id}}",
              "host": [
                "{{base_url}}"
              ],
              "path": [
                "api",
                "v1",
                "follow-ups",
                "{{follow_up_id}}"
              ]
            }
          },
          "response": []
        }
      ]
    },
    {
      "name": "Clients",
      "item": [
        {
          "name": "List Clients",
          "request": {
            "method": "GET",
            "header": [
              {
                "key": "Authorization",
                "value": "Bearer {{access_token}}"
              }
            ],
            "url": {
              "raw": "{{base_url}}/api/v1/clients",
              "host": [
                "{{base_url}}"
              ],
              "path": [
                "api",
                "v1",
                "clients"
              ]
            }
          },
          "response": []
        },
        {
          "name": "Show Client",
          "request": {
            "method": "GET",
            "header": [
              {
                "key": "Authorization",
                "value": "Bearer {{access_token}}"
              }
            ],
            "url": {
              "raw": "{{base_url}}/api/v1/clients/{{client_id}}",
              "host": [
                "{{base_url}}"
              ],
              "path": [
                "api",
                "v1",
                "clients",
                "{{client_id}}"
              ]
            }
          },
          "response": []
        },
        {
          "name": "Create Client",
          "request": {
            "method": "POST",
            "header": [
              {
                "key": "Authorization",
                "value": "Bearer {{access_token}}"
              },
              {
                "key": "Content-Type",
                "value": "application/json"
              }
            ],
            "body": {
              "mode": "raw",
              "raw": "{\n  \"name\": \"Acme Corp\",\n  \"email\": \"contact@acme.test\",\n  \"phone\": \"+1 555 123 4567\",\n  \"status\": \"warm\",\n  \"assigned_to\": {{user_id}}\n}"
            },
            "url": {
              "raw": "{{base_url}}/api/v1/clients",
              "host": [
                "{{base_url}}"
              ],
              "path": [
                "api",
                "v1",
                "clients"
              ]
            }
          },
          "response": []
        },
        {
          "name": "Update Client",
          "request": {
            "method": "PUT",
            "header": [
              {
                "key": "Authorization",
                "value": "Bearer {{access_token}}"
              },
              {
                "key": "Content-Type",
                "value": "application/json"
              }
            ],
            "body": {
              "mode": "raw",
              "raw": "{\n  \"name\": \"Acme Corp\",\n  \"email\": \"contact@acme.com\",\n  \"phone\": \"555-1234\",\n  \"company\": \"Acme Corporation\",\n  \"status\": \"hot\"\n}"
            },
            "url": {
              "raw": "{{base_url}}/api/v1/clients/{{client_id}}",
              "host": [
                "{{base_url}}"
              ],
              "path": [
                "api",
                "v1",
                "clients",
                "{{client_id}}"
              ]
            }
          },
          "response": []
        },
        {
          "name": "Delete Client",
          "request": {
            "method": "DELETE",
            "header": [
              {
                "key": "Authorization",
                "value": "Bearer {{access_token}}"
              }
            ],
            "url": {
              "raw": "{{base_url}}/api/v1/clients/{{client_id}}",
              "host": [
                "{{base_url}}"
              ],
              "path": [
                "api",
                "v1",
                "clients",
                "{{client_id}}"
              ]
            }
          },
          "response": []
        }
      ]
    },
    {
      "name": "Communications",
      "item": [
        {
          "name": "List Communications",
          "request": {
            "method": "GET",
            "header": [
              {
                "key": "Authorization",
                "value": "Bearer {{access_token}}"
              }
            ],
            "url": {
              "raw": "{{base_url}}/api/v1/clients/{{client_id}}/communications",
              "host": [
                "{{base_url}}"
              ],
              "path": [
                "api",
                "v1",
                "clients",
                "{{client_id}}",
                "communications"
              ]
            }
          },
          "response": []
        },
        {
          "name": "Add Communication",
          "request": {
            "method": "POST",
            "header": [
              {
                "key": "Authorization",
                "value": "Bearer {{access_token}}"
              },
              {
                "key": "Content-Type",
                "value": "application/json"
              }
            ],
            "body": {
              "mode": "raw",
              "raw": "{\n  \"type\": \"call\",\n  \"date\": \"2025-01-01T10:00:00Z\",\n  \"notes\": \"Discussed proposal\",\n  \"created_by\": {{user_id}}\n}"
            },
            "url": {
              "raw": "{{base_url}}/api/v1/clients/{{client_id}}/communications",
              "host": [
                "{{base_url}}"
              ],
              "path": [
                "api",
                "v1",
                "clients",
                "{{client_id}}",
                "communications"
              ]
            }
          },
          "response": []
        }
      ]
    },
    {
      "name": "Follow Ups",
      "item": [
        {
          "name": "List Follow Ups",
          "request": {
            "method": "GET",
            "header": [
              {
                "key": "Authorization",
                "value": "Bearer {{access_token}}"
              }
            ],
            "url": {
              "raw": "{{base_url}}/api/v1/clients/{{client_id}}/follow-ups",
              "host": [
                "{{base_url}}"
              ],
              "path": [
                "api",
                "v1",
                "clients",
                "{{client_id}}",
                "follow-ups"
              ]
            }
          },
          "response": []
        },
        {
          "name": "Create Follow Up",
          "request": {
            "method": "POST",
            "header": [
              {
                "key": "Authorization",
                "value": "Bearer {{access_token}}"
              },
              {
                "key": "Content-Type",
                "value": "application/json"
              }
            ],
            "body": {
              "mode": "raw",
              "raw": "{\n  \"due_date\": \"2025-01-02T09:00:00Z\",\n  \"notes\": \"Follow up on contract\"\n}"
            },
            "url": {
              "raw": "{{base_url}}/api/v1/clients/{{client_id}}/follow-ups",
              "host": [
                "{{base_url}}"
              ],
              "path": [
                "api",
                "v1",
                "clients",
                "{{client_id}}",
                "follow-ups"
              ]
            }
          },
          "response": []
        }
      ]
    },
    {
      "name": "Dashboard",
      "item": [
        {
          "name": "Get Dashboard Metrics",
          "request": {
            "method": "GET",
            "header": [
              {
                "key": "Authorization",
                "value": "Bearer {{access_token}}"
              }
            ],
            "url": {
              "raw": "{{base_url}}/api/v1/dashboard",
              "host": [
                "{{base_url}}"
              ],
              "path": [
                "api",
                "v1",
                "dashboard"
              ]
            }
          },
          "response": []
        }
      ]
    }
  ],
  "variable": [
    {
      "key": "base_url",
      "value": "http://localhost"
    },
    {
      "key": "access_token",
      "value": ""
    },
    {
      "key": "client_id",
      "value": "1"
    },
    {
      "key": "follow_up_id",
      "value": "1"
    },
    {
      "key": "user_id",
      "value": "1"
    }
  ]
}
